{
  "releases": {
    "stable": [
      {
        "id": "tastic-v0.0.5",
        "title": "Tastic Mesh Firmware v0.0.5",
        "page_url": "https://github.com/roperscrossroads/tasticfw/releases/tag/tastic-v0.0.5",
        "zip_url": "https://github.com/roperscrossroads/tasticfw/releases/download/tastic-v0.0.5/tastic-firmware-tastic-v0.0.5-all.zip",
        "release_notes": "Three board support! Added Heltec WiFi LoRa 32 V3. Includes firmware for nRF52840 devices (XIAO, Tracker) and ESP32-S3 devices (Heltec V3)."
      }
    ],
    "alpha": []
  },
  "pullRequests": []
}